Metadata-Version: 2.1
Name: cirmesh
Version: 0.0.18
Summary: basic
Home-page: https://github.com/thomle295/cirmesh
Author: ThomLe
Author-email: thomlestudy295@gmail.com
License: MIT
Platform: UNKNOWN
Classifier: License :: OSI Approved :: MIT License
Classifier: Programming Language :: Python :: 3
Classifier: Programming Language :: Python :: 3.7
Classifier: Programming Language :: Python :: 3.8
Classifier: Programming Language :: Python :: 3.9
License-File: LICENSE
